aliyunsdkxtrace/__init__.py
aliyunsdkxtrace/endpoint.py
aliyunsdkxtrace/request/__init__.py
aliyunsdkxtrace/request/v20190808/GetTagKeyRequest.py
aliyunsdkxtrace/request/v20190808/GetTagValRequest.py
aliyunsdkxtrace/request/v20190808/GetTokenRequest.py
aliyunsdkxtrace/request/v20190808/GetTraceAnalysisRequest.py
aliyunsdkxtrace/request/v20190808/GetTraceRequest.py
aliyunsdkxtrace/request/v20190808/ListIpOrHostsRequest.py
aliyunsdkxtrace/request/v20190808/ListServicesRequest.py
aliyunsdkxtrace/request/v20190808/ListSpanNamesRequest.py
aliyunsdkxtrace/request/v20190808/QueryMetricRequest.py
aliyunsdkxtrace/request/v20190808/SearchTracesRequest.py
aliyunsdkxtrace/request/v20190808/__init__.py
aliyun_python_sdk_xtrace-0.2.2.dist-info/LICENSE
aliyun_python_sdk_xtrace-0.2.2.dist-info/METADATA
aliyun_python_sdk_xtrace-0.2.2.dist-info/WHEEL
aliyun_python_sdk_xtrace-0.2.2.dist-info/top_level.txt
aliyun_python_sdk_xtrace-0.2.2.dist-info/RECORD
